{
  "id": 1002,
  "robots": [
    {"id": "snax", "name": "snäx"},
    {"id": "placeholder", "name": "%placeholder%"}
  ],
  "startingBaskets": ["magenta", "blue"],
  "isTieAllowed": false,
  "hasEnded": false,
  "rounds": [
    {
      "scores": [
        [
          {"time": 1669312847075, "isValid": true},
          {"time": 1669312860204, "isValid": true}
        ],
        [
          {"time": 1669312876912, "isValid": true},
          {"time": 1669312884430, "isValid": true}
        ]
      ],
      "fouls": [[], []],
      "baskets": ["magenta", "blue"],
      "hasEnded": true,
      "isConfirmed": true,
      "roundMaxLength": 60000,
      "runs": [{"startTime": 1669312840894, "endTime": 1669312900994}]
    },
    {
      "scores": [[], []],
      "fouls": [[], []],
      "baskets": ["blue", "magenta"],
      "hasEnded": false,
      "isConfirmed": false,
      "roundMaxLength": 60000,
      "runs": []
    }
  ],
  "ballPlacement": [
    [0, 0],
    [0.94, 1.27],
    [-0.94, -1.27],
    [-0.41, -1.24],
    [0.41, 1.24],
    [1.35, 0.48],
    [-1.35, -0.48],
    [1.65, -0.21],
    [-1.65, 0.21],
    [1.13, -0.28],
    [-1.13, 0.28]
  ]
}